{
  "taylor swift": "Taylor Swift",
  "post malone": "Post Malone",
  "justin bibber": "Justin Bibber",
  "台北": "台北",
  "ive": "IVE",
  "五月天": "五月天",
  "台南": "台南",
  "陳奕迅": "陳奕迅",
  "台東": "台東",
  "林俊傑": "林俊傑",
  "花蓮": "花蓮",
  "周杰倫": "周杰倫",
  "王力宏": "王力宏",
  "蕭敬騰": "蕭敬騰",
  "a-lin": "A-Lin",
  "台中": "台中",
  "蔡依林": "蔡依林",
  "周興哲": "周興哲",
  "g.e.m.": "G.E.M.",
  "mayday": "Mayday",
  "莫文蔚": "莫文蔚",
  "張學友": "張學友",
  "鄧紫棋": "鄧紫棋",
  "蘇打綠": "蘇打綠",
  "劉德華": "劉德華",
  "田馥甄": "田馥甄",
  "盧廣仲": "盧廣仲",
  "王心凌": "王心凌",
  "韋禮安": "韋禮安",
  "李宇春": "李宇春",
  "張惠妹": "張惠妹",
  "那英": "那英",
  "明天": "明天",
  "明年": "明年",
  "桃園": "桃園",
  "基隆": "基隆",
  "屏東": "屏東",
  "下個月": "下個月",
  "後天": "後天",
  "下周": "下周"
}